setup.py
pit/pit.py
python_pit.egg-info/PKG-INFO
python_pit.egg-info/SOURCES.txt
python_pit.egg-info/dependency_links.txt
python_pit.egg-info/entry_points.txt
python_pit.egg-info/top_level.txt