Metadata-Version: 1.1
Name: python-pit
Version: 0.2.0
Summary: Python as a stream filter
Home-page: https://github.com/samzhang111/pit
Author: Sam Zhang
Author-email: shimian.zhang@gmail.com
License: GNU GPL
Platform: UNKNOWN
Classifier: Development Status :: 3 - Alpha
Classifier: Intended Audience :: Developers
Classifier: License :: OSI Approved :: GNU General Public License (GPL)
Classifier: Topic :: Utilities
Classifier: Programming Language :: Python :: 2.6
Classifier: Programming Language :: Python :: 2.7
Classifier: Natural Language :: English
